{
  "subject": "aws-ai-practitioner",
  "topic": "exam-overview",
  "metadata": {
    "lastUpdated": "2024-12-19",
    "sources": [
      "AWS AI Practitioner Certification Exam Guide",
      "AWS Training and Certification",
      "AWS AI/ML Learning Path"
    ],
    "author": "Ben Green",
    "version": "1.0"
  },
  "cards": [
    {
      "id": 1,
      "question": "What is the AWS AI Practitioner certification code?",
      "answer": "AI1-C01"
    },
    {
      "id": 2,
      "question": "How long is the AWS AI Practitioner exam?",
      "answer": "90 minutes"
    },
    {
      "id": 3,
      "question": "What are the main domains covered in the AWS AI Practitioner exam?",
      "answer": "AI/ML fundamentals, AWS AI services, responsible AI practices, and AI use cases"
    },
    {
      "id": 4,
      "question": "What is the passing score for the AWS AI Practitioner exam?",
      "answer": "700 out of 1000 (scaled scoring)"
    },
    {
      "id": 5,
      "question": "What type of questions are on the AWS AI Practitioner exam?",
      "answer": "Multiple choice and multiple response questions"
    },
    {
      "id": 6,
      "question": "What is the cost of the AWS AI Practitioner exam?",
      "answer": "$100 USD"
    }
  ]
}